ourairports/__init__.py
ourairports/ourairports.py
ourairports/data/airports.csv.gz
ourairports/data/countries.csv.gz
ourairports/data/frequencies.csv.gz
ourairports/data/navaids.csv.gz
ourairports/data/regions.csv.gz
ourairports/data/runways.csv.gz
ourairports-1.1.0.20220724.data/data/airports.csv.gz
ourairports-1.1.0.20220724.data/data/countries.csv.gz
ourairports-1.1.0.20220724.data/data/frequencies.csv.gz
ourairports-1.1.0.20220724.data/data/navaids.csv.gz
ourairports-1.1.0.20220724.data/data/regions.csv.gz
ourairports-1.1.0.20220724.data/data/runways.csv.gz
ourairports-1.1.0.20220724.dist-info/METADATA
ourairports-1.1.0.20220724.dist-info/WHEEL
ourairports-1.1.0.20220724.dist-info/top_level.txt
ourairports-1.1.0.20220724.dist-info/RECORD
