Metadata-Version: 2.1
Name: ourairports
Version: 1.1.0.20220724
Summary: ourairports is an excellent client side library for all your airport data needs
Home-page: https://github.com/matthewgall/ourairports
Author: Matthew Gall
Author-email: complaints@matthewgall.com
License: MIT
Platform: linux
Platform: windows
Platform: macos
Classifier: Development Status :: 4 - Beta
Classifier: Environment :: Console
Classifier: Intended Audience :: Developers
Classifier: License :: OSI Approved :: MIT License
Classifier: Programming Language :: Python :: 2
Classifier: Programming Language :: Python :: 3
Requires-Dist: geopy
